keat_scripts/__init__.py
keat_scripts/echo.sh
keat_scripts/release.sh
keats/__init__.py
keats/__version__.py
keats/changelog_utils.py
keats/find_utils.py
keats/hooks/__init__.py
keats/hooks/keats_version_up.py
keats/hooks/utils.py
keats/utils.py
keats-0.2.29.dist-info/entry_points.txt
keats-0.2.29.dist-info/LICENSE
keats-0.2.29.dist-info/WHEEL
keats-0.2.29.dist-info/METADATA
keats-0.2.29.dist-info/RECORD
