Metadata-Version: 2.1
Name: keats
Version: 0.2.29
Summary: Utilities for managing version, changelogs, and project releases.
Home-page: https://github.com/jvrana/keats
Author: Justin Vrana
Author-email: justin.vrana@gmail.com
Requires-Python: >=3.5,<4.0
Classifier: Programming Language :: Python :: 3
Classifier: Programming Language :: Python :: 3.5
Classifier: Programming Language :: Python :: 3.6
Classifier: Programming Language :: Python :: 3.7
Classifier: Programming Language :: Python :: 3.8
Classifier: Topic :: Software Development :: Build Tools
Classifier: Topic :: Software Development :: Libraries :: Python Modules
Requires-Dist: fire (>=0.1.3,<0.2.0)
Requires-Dist: poetry-setup (>=0.3.6,<0.4.0)
Requires-Dist: termcolor (>=1.1,<2.0)
Requires-Dist: toml (>=0.10.0,<0.11.0)
Project-URL: Documentation, https://github.com/jvrana/keats
Project-URL: Repository, https://github.com/jvrana/keats
